fb_scrape_public/__init__.py
fb_scrape_public/fb_scrape_public.py
fb_scrape_public-1.0.10.dist-info/DESCRIPTION.rst
fb_scrape_public-1.0.10.dist-info/METADATA
fb_scrape_public-1.0.10.dist-info/RECORD
fb_scrape_public-1.0.10.dist-info/WHEEL
fb_scrape_public-1.0.10.dist-info/metadata.json
fb_scrape_public-1.0.10.dist-info/top_level.txt
