Metadata-Version: 1.1
Name: fb_scrape_public
Version: 1.0.10
Summary: fb_scrape_public
Home-page: https://github.com/dfreelon/fb_scrape_public/
Author: Deen Freelon
Author-email: dfreelon@gmail.com
License: UNKNOWN
Download-URL: https://github.com/dfreelon/fb_scrape_public/archive/master.tar.gz
Keywords: facebook,data collection,CSV,big data
Platform: UNKNOWN
